{"owner_id": "1015140", "members": {"959636": {"last_star_ts": "0", "stars": 0, "completion_day_level": {}, "name": "neugartf", "global_score": 0, "id": "959636", "local_score": 0}, "1015140": {"name": "ma-re", "completion_day_level": {"1": {"1": {"get_star_ts": 1638340873}, "2": {"get_star_ts": 1638341425}}, "2": {"1": {"get_star_ts": 1638426469}, "2": {"get_star_ts": 1638426944}}, "3": {"2": {"get_star_ts": 1638548961}, "1": {"get_star_ts": 1638519823}}, "4": {"2": {"get_star_ts": 1638605747}, "1": {"get_star_ts": 1638605606}}}, "stars": 8, "last_star_ts": 1638605747, "local_score": 78, "global_score": 0, "id": "1015140"}, "1292125": {"stars": 0, "last_star_ts": "0", "completion_day_level": {}, "name": "the-new-dride", "global_score": 0, "id": "1292125", "local_score": 0}, "676383": {"name": "jsmunsch", "completion_day_level": {}, "last_star_ts": "0", "stars": 0, "local_score": 0, "global_score": 0, "id": "676383"}, "1169553": {"completion_day_level": {}, "name": "flk92", "stars": 0, "last_star_ts": "0", "local_score": 0, "id": "1169553", "global_score": 0}, "1016111": {"name": "Andrew Emmett", "completion_day_level": {"1": {"1": {"get_star_ts": 1638366085}, "2": {"get_star_ts": 1638370117}}, "2": {"2": {"get_star_ts": 1638430741}, "1": {"get_star_ts": 1638430597}}, "3": {"1": {"get_star_ts": 1638528500}, "2": {"get_star_ts": 1638568394}}, "4": {"1": {"get_star_ts": 1638623330}, "2": {"get_star_ts": 1638643374}}}, "stars": 8, "last_star_ts": 1638643374, "local_score": 65, "global_score": 0, "id": "1016111"}, "65509": {"completion_day_level": {"1": {"1": {"get_star_ts": 1638347171}, "2": {"get_star_ts": 1638347789}}, "2": {"2": {"get_star_ts": 1638431082}, "1": {"get_star_ts": 1638429305}}, "5": {"1": {"get_star_ts": 1638692046}, "2": {"get_star_ts": 1638694975}}, "4": {"1": {"get_star_ts": 1638610860}, "2": {"get_star_ts": 1638613153}}, "3": {"2": {"get_star_ts": 1638512527}, "1": {"get_star_ts": 1638510769}}}, "name": "terezaif", "stars": 10, "last_star_ts": 1638694975, "local_score": 93, "global_score": 0, "id": "65509"}, "1156146": {"last_star_ts": "0", "stars": 0, "name": "bwnstck", "completion_day_level": {}, "global_score": 0, "id": "1156146", "local_score": 0}, "1185220": {"name": "oem", "completion_day_level": {}, "last_star_ts": "0", "stars": 0, "local_score": 0, "id": "1185220", "global_score": 0}, "1220886": {"name": "olehansen538", "completion_day_level": {}, "stars": 0, "last_star_ts": "0", "local_score": 0, "id": "1220886", "global_score": 0}}, "event": "2021"}