{"members": {"1642944": {"stars": 0, "completion_day_level": {}, "name": "nklausner", "id": "1642944", "last_star_ts": "0", "local_score": 0, "global_score": 0}, "1600033": {"local_score": 0, "last_star_ts": "0", "global_score": 0, "id": "1600033", "name": "fasoula", "completion_day_level": {}, "stars": 0}, "65509": {"global_score": 0, "last_star_ts": 1608889880, "local_score": 801, "id": "65509", "name": "terezaif", "completion_day_level": {"2": {"1": {"get_star_ts": 1606912702}, "2": {"get_star_ts": 1606915898}}, "13": {"1": {"get_star_ts": 1607847637}, "2": {"get_star_ts": 1607859934}}, "14": {"1": {"get_star_ts": 1607940463}, "2": {"get_star_ts": 1607972840}}, "15": {"1": {"get_star_ts": 1608013321}, "2": {"get_star_ts": 1608013640}}, "4": {"1": {"get_star_ts": 1607060766}, "2": {"get_star_ts": 1607068693}}, "16": {"2": {"get_star_ts": 1608159073}, "1": {"get_star_ts": 1608142623}}, "19": {"1": {"get_star_ts": 1608407540}, "2": {"get_star_ts": 1608418382}}, "18": {"1": {"get_star_ts": 1608284186}, "2": {"get_star_ts": 1608286010}}, "9": {"1": {"get_star_ts": 1607492515}, "2": {"get_star_ts": 1607493650}}, "3": {"2": {"get_star_ts": 1607011789}, "1": {"get_star_ts": 1607010981}}, "23": {"1": {"get_star_ts": 1608718923}, "2": {"get_star_ts": 1608889865}}, "7": {"1": {"get_star_ts": 1607325137}, "2": {"get_star_ts": 1607354977}}, "25": {"2": {"get_star_ts": 1608889880}, "1": {"get_star_ts": 1608889222}}, "12": {"1": {"get_star_ts": 1607769288}, "2": {"get_star_ts": 1607771586}}, "17": {"1": {"get_star_ts": 1608238637}, "2": {"get_star_ts": 1608239116}}, "5": {"1": {"get_star_ts": 1607147108}, "2": {"get_star_ts": 1607147461}}, "11": {"2": {"get_star_ts": 1607716315}, "1": {"get_star_ts": 1607697748}}, "24": {"1": {"get_star_ts": 1608804070}, "2": {"get_star_ts": 1608830670}}, "1": {"2": {"get_star_ts": 1606841942}, "1": {"get_star_ts": 1606841796}}, "8": {"1": {"get_star_ts": 1607406637}, "2": {"get_star_ts": 1607408584}}, "6": {"1": {"get_star_ts": 1607232076}, "2": {"get_star_ts": 1607232689}}, "22": {"2": {"get_star_ts": 1608624577}, "1": {"get_star_ts": 1608618547}}, "21": {"2": {"get_star_ts": 1608592915}, "1": {"get_star_ts": 1608591394}}, "20": {"2": {"get_star_ts": 1608889760}, "1": {"get_star_ts": 1608477817}}, "10": {"1": {"get_star_ts": 1607578706}, "2": {"get_star_ts": 1607584574}}}, "stars": 50}, "674838": {"id": "674838", "last_star_ts": 1608915765, "local_score": 781, "global_score": 0, "stars": 48, "name": "Leli", "completion_day_level": {"16": {"2": {"get_star_ts": 1608107225}, "1": {"get_star_ts": 1608105486}}, "14": {"2": {"get_star_ts": 1607959062}, "1": {"get_star_ts": 1607933629}}, "4": {"2": {"get_star_ts": 1607060900}, "1": {"get_star_ts": 1607059484}}, "15": {"2": {"get_star_ts": 1608020469}, "1": {"get_star_ts": 1608020372}}, "13": {"1": {"get_star_ts": 1607847726}, "2": {"get_star_ts": 1607866330}}, "2": {"1": {"get_star_ts": 1606896221}, "2": {"get_star_ts": 1606897167}}, "23": {"1": {"get_star_ts": 1608714764}, "2": {"get_star_ts": 1608715287}}, "7": {"1": {"get_star_ts": 1607331803}, "2": {"get_star_ts": 1607336366}}, "3": {"1": {"get_star_ts": 1606984877}, "2": {"get_star_ts": 1606985833}}, "19": {"2": {"get_star_ts": 1608375244}, "1": {"get_star_ts": 1608374922}}, "18": {"1": {"get_star_ts": 1608377903}, "2": {"get_star_ts": 1608415030}}, "9": {"2": {"get_star_ts": 1607491085}, "1": {"get_star_ts": 1607490731}}, "1": {"2": {"get_star_ts": 1606810583}, "1": {"get_star_ts": 1606810397}}, "24": {"1": {"get_star_ts": 1608800939}, "2": {"get_star_ts": 1608829252}}, "17": {"2": {"get_star_ts": 1608552332}, "1": {"get_star_ts": 1608551537}}, "11": {"1": {"get_star_ts": 1607711892}, "2": {"get_star_ts": 1607715895}}, "5": {"1": {"get_star_ts": 1607157987}, "2": {"get_star_ts": 1607158307}}, "25": {"1": {"get_star_ts": 1608915765}}, "12": {"1": {"get_star_ts": 1607760018}, "2": {"get_star_ts": 1607761823}}, "10": {"2": {"get_star_ts": 1607592042}, "1": {"get_star_ts": 1607584078}}, "20": {"1": {"get_star_ts": 1608455038}}, "21": {"2": {"get_star_ts": 1608542378}, "1": {"get_star_ts": 1608542029}}, "22": {"2": {"get_star_ts": 1608629030}, "1": {"get_star_ts": 1608624627}}, "6": {"1": {"get_star_ts": 1607248851}, "2": {"get_star_ts": 1607249380}}, "8": {"2": {"get_star_ts": 1607404887}, "1": {"get_star_ts": 1607404350}}}}, "1491099": {"name": "Brunno Gorgulho Soares", "completion_day_level": {"1": {"1": {"get_star_ts": 1636358593}}}, "stars": 1, "last_star_ts": 1636358593, "local_score": 0, "global_score": 0, "id": "1491099"}, "974152": {"stars": 25, "completion_day_level": {"4": {"1": {"get_star_ts": 1607067317}, "2": {"get_star_ts": 1607069226}}, "12": {"1": {"get_star_ts": 1607814352}, "2": {"get_star_ts": 1607815546}}, "2": {"2": {"get_star_ts": 1606892343}, "1": {"get_star_ts": 1606891914}}, "13": {"1": {"get_star_ts": 1607848818}, "2": {"get_star_ts": 1607858490}}, "1": {"2": {"get_star_ts": 1606806573}, "1": {"get_star_ts": 1606806123}}, "11": {"1": {"get_star_ts": 1607812462}}, "5": {"1": {"get_star_ts": 1607158689}, "2": {"get_star_ts": 1607159327}}, "3": {"1": {"get_star_ts": 1606980553}, "2": {"get_star_ts": 1606980666}}, "8": {"1": {"get_star_ts": 1607409091}, "2": {"get_star_ts": 1607409734}}, "6": {"2": {"get_star_ts": 1607241688}, "1": {"get_star_ts": 1607241212}}, "9": {"1": {"get_star_ts": 1607496891}, "2": {"get_star_ts": 1607497946}}, "10": {"2": {"get_star_ts": 1607588039}, "1": {"get_star_ts": 1607583937}}, "7": {"2": {"get_star_ts": 1607327403}, "1": {"get_star_ts": 1607326103}}}, "name": "Oliver Sieweke", "id": "974152", "last_star_ts": 1607858490, "global_score": 0, "local_score": 373}, "988507": {"last_star_ts": 1607862426, "local_score": 345, "global_score": 0, "id": "988507", "completion_day_level": {"12": {"2": {"get_star_ts": 1607794710}, "1": {"get_star_ts": 1607786556}}, "4": {"2": {"get_star_ts": 1607086945}, "1": {"get_star_ts": 1607069945}}, "2": {"2": {"get_star_ts": 1606920625}, "1": {"get_star_ts": 1606919439}}, "13": {"1": {"get_star_ts": 1607862426}}, "1": {"2": {"get_star_ts": 1606820811}, "1": {"get_star_ts": 1606812502}}, "11": {"1": {"get_star_ts": 1607721867}, "2": {"get_star_ts": 1607724769}}, "5": {"2": {"get_star_ts": 1607157203}, "1": {"get_star_ts": 1607155975}}, "3": {"1": {"get_star_ts": 1606982896}, "2": {"get_star_ts": 1606997546}}, "8": {"1": {"get_star_ts": 1607411525}, "2": {"get_star_ts": 1607418663}}, "6": {"2": {"get_star_ts": 1607250987}, "1": {"get_star_ts": 1607242676}}, "9": {"2": {"get_star_ts": 1607498267}, "1": {"get_star_ts": 1607497020}}, "10": {"2": {"get_star_ts": 1607609882}, "1": {"get_star_ts": 1607582970}}, "7": {"2": {"get_star_ts": 1607350487}, "1": {"get_star_ts": 1607329399}}}, "name": "Anna", "stars": 25}, "1540216": {"id": "1540216", "last_star_ts": "0", "local_score": 0, "global_score": 0, "stars": 0, "name": "Evan Simpson", "completion_day_level": {}}, "1016111": {"stars": 20, "completion_day_level": {"5": {"2": {"get_star_ts": 1607200144}, "1": {"get_star_ts": 1607198790}}, "1": {"1": {"get_star_ts": 1606818549}, "2": {"get_star_ts": 1606818840}}, "2": {"2": {"get_star_ts": 1606898538}, "1": {"get_star_ts": 1606898143}}, "13": {"1": {"get_star_ts": 1638049864}, "2": {"get_star_ts": 1638054923}}, "12": {"2": {"get_star_ts": 1638043334}, "1": {"get_star_ts": 1638021105}}, "4": {"2": {"get_star_ts": 1607195400}, "1": {"get_star_ts": 1607081030}}, "6": {"2": {"get_star_ts": 1607286525}, "1": {"get_star_ts": 1607284637}}, "8": {"2": {"get_star_ts": 1637953665}, "1": {"get_star_ts": 1637945168}}, "9": {"1": {"get_star_ts": 1638015870}, "2": {"get_star_ts": 1638016603}}, "3": {"1": {"get_star_ts": 1606982914}, "2": {"get_star_ts": 1607011096}}}, "name": "adriz-nf", "id": "1016111", "global_score": 0, "last_star_ts": 1638054923, "local_score": 230}, "1591363": {"stars": 0, "name": null, "completion_day_level": {}, "id": "1591363", "last_star_ts": "0", "global_score": 0, "local_score": 0}, "1587041": {"id": "1587041", "last_star_ts": "0", "global_score": 0, "local_score": 0, "stars": 0, "completion_day_level": {}, "name": "Dania Meira"}, "1586015": {"name": "rmohr", "completion_day_level": {}, "stars": 0, "last_star_ts": "0", "global_score": 0, "local_score": 0, "id": "1586015"}, "1026950": {"id": "1026950", "local_score": 550, "last_star_ts": 1609000050, "global_score": 0, "stars": 39, "name": "bonartm", "completion_day_level": {"3": {"1": {"get_star_ts": 1607006023}, "2": {"get_star_ts": 1607006402}}, "18": {"2": {"get_star_ts": 1608305180}, "1": {"get_star_ts": 1608302230}}, "9": {"2": {"get_star_ts": 1607533495}, "1": {"get_star_ts": 1607533007}}, "7": {"1": {"get_star_ts": 1607426582}, "2": {"get_star_ts": 1607427658}}, "14": {"1": {"get_star_ts": 1607947958}, "2": {"get_star_ts": 1607962716}}, "4": {"1": {"get_star_ts": 1607075912}, "2": {"get_star_ts": 1607077814}}, "15": {"2": {"get_star_ts": 1608032181}, "1": {"get_star_ts": 1608027906}}, "13": {"2": {"get_star_ts": 1607886014}, "1": {"get_star_ts": 1607854055}}, "2": {"2": {"get_star_ts": 1606927350}, "1": {"get_star_ts": 1606925894}}, "16": {"1": {"get_star_ts": 1608112183}, "2": {"get_star_ts": 1608115238}}, "8": {"1": {"get_star_ts": 1607428725}, "2": {"get_star_ts": 1607430332}}, "6": {"2": {"get_star_ts": 1607423849}, "1": {"get_star_ts": 1607423370}}, "10": {"2": {"get_star_ts": 1607640171}, "1": {"get_star_ts": 1607599622}}, "25": {"1": {"get_star_ts": 1609000050}}, "12": {"1": {"get_star_ts": 1607775279}, "2": {"get_star_ts": 1607777251}}, "1": {"1": {"get_star_ts": 1606828749}, "2": {"get_star_ts": 1606829059}}, "24": {"2": {"get_star_ts": 1608821851}, "1": {"get_star_ts": 1608819462}}, "17": {"2": {"get_star_ts": 1608197560}, "1": {"get_star_ts": 1608197279}}, "5": {"2": {"get_star_ts": 1607169835}, "1": {"get_star_ts": 1607169405}}, "11": {"2": {"get_star_ts": 1607682931}, "1": {"get_star_ts": 1607678386}}}}, "1591633": {"completion_day_level": {}, "name": "Maxim Yushin", "stars": 0, "global_score": 0, "last_star_ts": "0", "local_score": 0, "id": "1591633"}, "1585836": {"completion_day_level": {}, "name": "rogall-e", "stars": 0, "last_star_ts": "0", "global_score": 0, "local_score": 0, "id": "1585836"}, "1005598": {"last_star_ts": 1609400254, "global_score": 0, "local_score": 93, "id": "1005598", "completion_day_level": {"22": {"1": {"get_star_ts": 1608657893}}, "4": {"1": {"get_star_ts": 1609400254}}, "3": {"2": {"get_star_ts": 1606986089}, "1": {"get_star_ts": 1606985286}}, "2": {"2": {"get_star_ts": 1606922390}, "1": {"get_star_ts": 1606921394}}, "1": {"2": {"get_star_ts": 1606841680}, "1": {"get_star_ts": 1606812483}}, "24": {"1": {"get_star_ts": 1609100360}}}, "name": "Ben", "stars": 9}, "966061": {"last_star_ts": 1608873632, "local_score": 903, "global_score": 0, "id": "966061", "completion_day_level": {"6": {"2": {"get_star_ts": 1607231553}, "1": {"get_star_ts": 1607231451}}, "8": {"2": {"get_star_ts": 1607404769}, "1": {"get_star_ts": 1607404046}}, "22": {"2": {"get_star_ts": 1608614892}, "1": {"get_star_ts": 1608613673}}, "21": {"2": {"get_star_ts": 1608530036}, "1": {"get_star_ts": 1608529143}}, "20": {"1": {"get_star_ts": 1608442185}, "2": {"get_star_ts": 1608446126}}, "10": {"2": {"get_star_ts": 1607578590}, "1": {"get_star_ts": 1607577281}}, "25": {"1": {"get_star_ts": 1608873573}, "2": {"get_star_ts": 1608873632}}, "12": {"1": {"get_star_ts": 1607749648}, "2": {"get_star_ts": 1607750835}}, "17": {"2": {"get_star_ts": 1608184629}, "1": {"get_star_ts": 1608184222}}, "5": {"1": {"get_star_ts": 1607145080}, "2": {"get_star_ts": 1607145353}}, "11": {"1": {"get_star_ts": 1607664539}, "2": {"get_star_ts": 1607665408}}, "24": {"1": {"get_star_ts": 1608787104}, "2": {"get_star_ts": 1608788225}}, "1": {"1": {"get_star_ts": 1606812676}, "2": {"get_star_ts": 1606812850}}, "18": {"1": {"get_star_ts": 1608269223}, "2": {"get_star_ts": 1608269506}}, "19": {"2": {"get_star_ts": 1608359426}, "1": {"get_star_ts": 1608357745}}, "9": {"1": {"get_star_ts": 1607490611}, "2": {"get_star_ts": 1607491010}}, "3": {"1": {"get_star_ts": 1606974264}, "2": {"get_star_ts": 1606974625}}, "23": {"2": {"get_star_ts": 1608703763}, "1": {"get_star_ts": 1608700367}}, "7": {"1": {"get_star_ts": 1607318076}, "2": {"get_star_ts": 1607318898}}, "13": {"2": {"get_star_ts": 1607843886}, "1": {"get_star_ts": 1607836245}}, "2": {"1": {"get_star_ts": 1606906510}, "2": {"get_star_ts": 1606916745}}, "14": {"2": {"get_star_ts": 1607925838}, "1": {"get_star_ts": 1607922891}}, "15": {"2": {"get_star_ts": 1608010129}, "1": {"get_star_ts": 1608009868}}, "4": {"1": {"get_star_ts": 1607058450}, "2": {"get_star_ts": 1607059431}}, "16": {"2": {"get_star_ts": 1608099759}, "1": {"get_star_ts": 1608095924}}}, "name": "Kristian Rother", "stars": 50}, "1252785": {"name": "Magdalena Rother", "completion_day_level": {"18": {"1": {"get_star_ts": 1609370013}, "2": {"get_star_ts": 1609371550}}, "19": {"1": {"get_star_ts": 1609622920}, "2": {"get_star_ts": 1609880050}}, "9": {"1": {"get_star_ts": 1608498036}, "2": {"get_star_ts": 1608499832}}, "3": {"2": {"get_star_ts": 1608047060}, "1": {"get_star_ts": 1608045895}}, "7": {"2": {"get_star_ts": 1608446096}, "1": {"get_star_ts": 1608403868}}, "23": {"2": {"get_star_ts": 1609766916}, "1": {"get_star_ts": 1608763031}}, "2": {"1": {"get_star_ts": 1607791578}, "2": {"get_star_ts": 1607792426}}, "13": {"1": {"get_star_ts": 1607837927}, "2": {"get_star_ts": 1607897320}}, "14": {"2": {"get_star_ts": 1607989518}, "1": {"get_star_ts": 1607957993}}, "4": {"1": {"get_star_ts": 1607803952}, "2": {"get_star_ts": 1607810768}}, "15": {"1": {"get_star_ts": 1608037326}, "2": {"get_star_ts": 1608037697}}, "16": {"1": {"get_star_ts": 1608322727}, "2": {"get_star_ts": 1608333063}}, "6": {"1": {"get_star_ts": 1608067365}, "2": {"get_star_ts": 1608068486}}, "8": {"1": {"get_star_ts": 1608417963}, "2": {"get_star_ts": 1608455977}}, "22": {"1": {"get_star_ts": 1608620635}, "2": {"get_star_ts": 1608670923}}, "21": {"1": {"get_star_ts": 1608546670}, "2": {"get_star_ts": 1608552721}}, "20": {"2": {"get_star_ts": 1608756185}, "1": {"get_star_ts": 1608464855}}, "10": {"1": {"get_star_ts": 1607578443}, "2": {"get_star_ts": 1607634617}}, "25": {"1": {"get_star_ts": 1609187685}, "2": {"get_star_ts": 1609880107}}, "12": {"1": {"get_star_ts": 1607752400}, "2": {"get_star_ts": 1607755757}}, "17": {"2": {"get_star_ts": 1609420854}, "1": {"get_star_ts": 1609420372}}, "5": {"2": {"get_star_ts": 1608065256}, "1": {"get_star_ts": 1608060845}}, "11": {"2": {"get_star_ts": 1607764088}, "1": {"get_star_ts": 1607723868}}, "1": {"1": {"get_star_ts": 1607641432}, "2": {"get_star_ts": 1607641919}}, "24": {"2": {"get_star_ts": 1608996615}, "1": {"get_star_ts": 1608934509}}}, "stars": 50, "local_score": 685, "last_star_ts": 1609880107, "global_score": 0, "id": "1252785"}, "966291": {"last_star_ts": 1609323006, "local_score": 296, "global_score": 0, "id": "966291", "name": null, "completion_day_level": {"14": {"2": {"get_star_ts": 1609168308}, "1": {"get_star_ts": 1608914959}}, "4": {"2": {"get_star_ts": 1607090194}, "1": {"get_star_ts": 1607070055}}, "12": {"1": {"get_star_ts": 1608221858}}, "15": {"1": {"get_star_ts": 1609172592}}, "2": {"1": {"get_star_ts": 1606903109}, "2": {"get_star_ts": 1606904842}}, "13": {"1": {"get_star_ts": 1608455178}}, "1": {"1": {"get_star_ts": 1606828426}, "2": {"get_star_ts": 1606828986}}, "16": {"1": {"get_star_ts": 1609323006}}, "5": {"2": {"get_star_ts": 1607286471}, "1": {"get_star_ts": 1607161141}}, "3": {"2": {"get_star_ts": 1606997419}, "1": {"get_star_ts": 1606995036}}, "8": {"1": {"get_star_ts": 1607877350}, "2": {"get_star_ts": 1607955450}}, "6": {"1": {"get_star_ts": 1607290342}, "2": {"get_star_ts": 1607297389}}, "9": {"2": {"get_star_ts": 1607791428}, "1": {"get_star_ts": 1607789397}}, "10": {"1": {"get_star_ts": 1607978730}}, "7": {"1": {"get_star_ts": 1607596306}}}, "stars": 24}}, "owner_id": "966061", "event": "2020"}